{
  "displayProperties": {
    "description": "",
    "name": "Modificador de granada",
    "icon": "/common/destiny2_content/icons/774854aa449ce8053f708b88d10d35c5.png",
    "iconHash": 0,
    "iconSequences": [
      {
        "frames": [
          "/common/destiny2_content/icons/774854aa449ce8053f708b88d10d35c5.png"
        ]
      },
      {
        "frames": [
          "/common/destiny2_content/icons/e917932080e5a5b4ddd12017fd374f20.png"
        ]
      }
    ],
    "hasIcon": true
  },
  "scope": 0,
  "sourceString": "Requiere el nivel de guardián 3",
  "sourceHash": 2278847330,
  "itemHash": 1435557120,
  "acquisitionInfo": {
    "runOnlyAcquisitionRewardSite": false
  },
  "stateInfo": {
    "requirements": {
      "entitlementUnavailableMessage": ""
    }
  },
  "presentationNodeType": 1,
  "traitIds": [],
  "traitHashes": [],
  "parentNodeHashes": [
    1929360037
  ],
  "hash": 2145798388,
  "index": 5684,
  "redacted": false,
  "blacklisted": false
}
