{
  "displayProperties": {
    "description": "Equipa este diseño en cualquier armadura de leyenda apta para cambiar su apariencia. Cuando obtienes un diseño universal, se desbloquea para todos los personajes de la clase correspondiente de tu cuenta.",
    "name": "Túnica Cárabo Opulento",
    "icon": "/common/destiny2_content/icons/d666ce087be3568163c9ffd57b923146.jpg",
    "iconHash": 0,
    "highResIcon": "/common/destiny2_content/icons/52ece9f5e93da4843c61de698e969daa.jpg",
    "hasIcon": true
  },
  "scope": 0,
  "sourceString": "Fuente: Eververso",
  "sourceHash": 860688654,
  "itemHash": 1673857967,
  "acquisitionInfo": {
    "runOnlyAcquisitionRewardSite": false
  },
  "stateInfo": {
    "requirements": {
      "entitlementUnavailableMessage": ""
    }
  },
  "presentationNodeType": 1,
  "traitIds": [],
  "traitHashes": [],
  "parentNodeHashes": [
    3995777969
  ],
  "hash": 27567783,
  "index": 3965,
  "redacted": false,
  "blacklisted": false
}
