{
  "displayProperties": {
    "description": "Equipe este ornamento de arma para mudar a aparência da Colônia. Quando você ganha um ornamento, ele fica desbloqueado para todos os personagens na sua conta.",
    "name": "Ataque Surpresa",
    "icon": "/common/destiny2_content/icons/536f9b6f8ff44e4fb817c5fa9a1f8866.jpg",
    "iconHash": 0,
    "highResIcon": "/common/destiny2_content/icons/d37551239e436d7cef805f102a8ca532.jpg",
    "hasIcon": true
  },
  "scope": 0,
  "sourceString": "Fonte: Eververso",
  "sourceHash": 860688654,
  "itemHash": 4252160794,
  "acquisitionInfo": {
    "runOnlyAcquisitionRewardSite": false
  },
  "stateInfo": {
    "requirements": {
      "entitlementUnavailableMessage": ""
    }
  },
  "presentationNodeType": 1,
  "traitIds": [],
  "traitHashes": [],
  "parentNodeHashes": [
    3069957704
  ],
  "hash": 1327459360,
  "index": 4799,
  "redacted": false,
  "blacklisted": false
}
