{
  "displayProperties": {
    "description": "Equipe este ornamento para mudar a aparência do Divisor de Ondas. Quando você ganha um ornamento, ele fica desbloqueado para todos os personagens na sua conta.",
    "name": "Pseudociência",
    "icon": "/common/destiny2_content/icons/4f530b6b5b1bb09fafff66c871091e83.jpg",
    "iconHash": 0,
    "highResIcon": "/common/destiny2_content/icons/10b1fb49a3461ea78628191edd0b20b5.jpg",
    "hasIcon": true
  },
  "scope": 0,
  "sourceString": "Fonte: Eververso",
  "sourceHash": 860688654,
  "itemHash": 3142425843,
  "acquisitionInfo": {
    "runOnlyAcquisitionRewardSite": false
  },
  "stateInfo": {
    "requirements": {
      "entitlementUnavailableMessage": ""
    }
  },
  "presentationNodeType": 1,
  "traitIds": [],
  "traitHashes": [],
  "parentNodeHashes": [
    4217199023
  ],
  "hash": 3925498229,
  "index": 5099,
  "redacted": false,
  "blacklisted": false
}
