{
  "displayProperties": {
    "description": "",
    "name": "Gwiazdorska wstęga",
    "icon": "/common/destiny2_content/icons/0f23fc381cf114766b22679899c863fc.jpg",
    "iconHash": 0,
    "hasIcon": true
  },
  "scope": 1,
  "sourceString": "Źródło: Zawody Strażników 2024",
  "sourceHash": 1568732528,
  "itemHash": 3720087872,
  "acquisitionInfo": {
    "runOnlyAcquisitionRewardSite": false
  },
  "stateInfo": {
    "requirements": {
      "entitlementUnavailableMessage": ""
    }
  },
  "presentationNodeType": 1,
  "traitIds": [],
  "traitHashes": [],
  "parentNodeHashes": [
    673009848
  ],
  "hash": 1539272877,
  "index": 1976,
  "redacted": false,
  "blacklisted": false
}
