{
  "displayProperties": {
    "description": "",
    "name": "Poza grawitacją",
    "icon": "/common/destiny2_content/icons/bc95b98fc738ac946dd035eb956a44de.jpg",
    "iconHash": 0,
    "hasIcon": true
  },
  "scope": 0,
  "sourceString": "Źródło: do odblokowania dzięki specjalnej ofercie.",
  "sourceHash": 1358645302,
  "itemHash": 4099900662,
  "acquisitionInfo": {
    "runOnlyAcquisitionRewardSite": false
  },
  "stateInfo": {
    "requirements": {
      "entitlementUnavailableMessage": "Ekskluzywny przedmiot"
    }
  },
  "presentationNodeType": 1,
  "traitIds": [],
  "traitHashes": [],
  "parentNodeHashes": [
    1166184619
  ],
  "hash": 1720952420,
  "index": 6448,
  "redacted": false,
  "blacklisted": false
}
