{
  "displayProperties": {
    "description": "Użyj tego zdobienia broni, aby zmienić wygląd Czarnego pazura. Kiedy otrzymasz zdobienie, zostanie ono odblokowane dla wszystkich postaci na danym koncie.",
    "name": "Splątany paladyn",
    "icon": "/common/destiny2_content/icons/165ad05c581f0d3bc5d010e75fa32ef7.jpg",
    "iconHash": 0,
    "highResIcon": "/common/destiny2_content/icons/be5805799e555c7c8f606823bd4ccccc.jpg",
    "hasIcon": true
  },
  "scope": 0,
  "sourceString": "Źródło: Eververse",
  "sourceHash": 860688654,
  "itemHash": 2117927723,
  "acquisitionInfo": {
    "runOnlyAcquisitionRewardSite": false
  },
  "stateInfo": {
    "requirements": {
      "entitlementUnavailableMessage": ""
    }
  },
  "presentationNodeType": 1,
  "traitIds": [],
  "traitHashes": [],
  "parentNodeHashes": [
    895842570
  ],
  "hash": 20092429,
  "index": 5072,
  "redacted": false,
  "blacklisted": false
}
