{
  "displayProperties": {
    "description": "Użyj tego zdobienia na odpowiednim legendarnym zestawie pancerza, by zmienić jego wygląd. Gdy zdobędziesz uniwersalne zdobienie, zostanie ono odblokowane dla wszystkich postaci na danym koncie.",
    "name": "Buty Doki Doki Destiny dla Łowcy",
    "icon": "/common/destiny2_content/icons/16162ed112ca52ece02c4ad9cdc69532.jpg",
    "iconHash": 0,
    "highResIcon": "/common/destiny2_content/icons/8a0f8a96d167a2c407190ef53e589084.jpg",
    "hasIcon": true
  },
  "scope": 0,
  "sourceString": "Źródło: Eververse",
  "sourceHash": 860688654,
  "itemHash": 3257350604,
  "acquisitionInfo": {
    "runOnlyAcquisitionRewardSite": false
  },
  "stateInfo": {
    "requirements": {
      "entitlementUnavailableMessage": ""
    }
  },
  "presentationNodeType": 1,
  "traitIds": [],
  "traitHashes": [],
  "parentNodeHashes": [
    188965629
  ],
  "hash": 247323592,
  "index": 1297,
  "redacted": false,
  "blacklisted": false
}
