{
  "displayProperties": {
    "description": "Użyj tego zdobienia na odpowiednim legendarnym zestawie pancerza, by zmienić jego wygląd. Gdy zdobędziesz uniwersalne zdobienie, zostanie ono odblokowane dla wszystkich postaci na danym koncie.",
    "name": "Szaty nadmorskiej celebracji",
    "icon": "/common/destiny2_content/icons/6ba486d4c848dd463860b6b1189dde93.jpg",
    "iconHash": 0,
    "highResIcon": "/common/destiny2_content/icons/883edf728abf93b848dd2f91f17c4d64.jpg",
    "hasIcon": true
  },
  "scope": 0,
  "sourceString": "Źródło: Eververse",
  "sourceHash": 860688654,
  "itemHash": 2135043770,
  "acquisitionInfo": {
    "runOnlyAcquisitionRewardSite": false
  },
  "stateInfo": {
    "requirements": {
      "entitlementUnavailableMessage": ""
    }
  },
  "presentationNodeType": 1,
  "traitIds": [],
  "traitHashes": [],
  "parentNodeHashes": [
    4016952119
  ],
  "hash": 3681880708,
  "index": 4330,
  "redacted": false,
  "blacklisted": false
}
