{
  "displayProperties": {
    "description": "Użyj tego zdobienia na odpowiednim legendarnym zestawie pancerza, by zmienić jego wygląd. Gdy zdobędziesz uniwersalne zdobienie, zostanie ono odblokowane dla wszystkich postaci na danym koncie.",
    "name": "Buty pryzmatu białego żaru",
    "icon": "/common/destiny2_content/icons/58f87dc431114b215c74ca992c9303c1.jpg",
    "iconHash": 0,
    "hasIcon": true
  },
  "scope": 0,
  "sourceString": "Źródło: Eververse",
  "sourceHash": 860688654,
  "itemHash": 2177680704,
  "acquisitionInfo": {
    "runOnlyAcquisitionRewardSite": false
  },
  "stateInfo": {
    "requirements": {
      "entitlementUnavailableMessage": ""
    }
  },
  "presentationNodeType": 1,
  "traitIds": [],
  "traitHashes": [],
  "parentNodeHashes": [
    4067284878
  ],
  "hash": 738147963,
  "index": 4296,
  "redacted": false,
  "blacklisted": false
}
