{
  "displayProperties": {
    "description": "Użyj tego zdobienia broni, aby zmienić wygląd Asa pik. Kiedy otrzymasz zdobienie, zostanie ono odblokowane dla wszystkich postaci na danym koncie.",
    "name": "Pięćdziesiąty trzeci",
    "icon": "/common/destiny2_content/icons/2275d32ba18fb929f3eb57ad8756a116.jpg",
    "iconHash": 0,
    "highResIcon": "/common/destiny2_content/icons/51e455924c18b72761894425e27af8a1.jpg",
    "hasIcon": true
  },
  "scope": 0,
  "sourceString": "Źródło: Eververse",
  "sourceHash": 860688654,
  "itemHash": 2134412545,
  "acquisitionInfo": {
    "runOnlyAcquisitionRewardSite": false
  },
  "stateInfo": {
    "requirements": {
      "entitlementUnavailableMessage": ""
    }
  },
  "presentationNodeType": 1,
  "traitIds": [],
  "traitHashes": [],
  "parentNodeHashes": [
    414094560
  ],
  "hash": 821774734,
  "index": 4854,
  "redacted": false,
  "blacklisted": false
}
