{
  "displayProperties": {
    "description": "",
    "name": "Destrier d'Avalon",
    "icon": "/common/destiny2_content/icons/93465412c6ec3c23adb5d47ef31f5006.jpg",
    "iconHash": 0,
    "hasIcon": true
  },
  "scope": 0,
  "sourceString": "Source : engrammes brillants",
  "sourceHash": 4036739795,
  "itemHash": 3610177557,
  "acquisitionInfo": {
    "acquireMaterialRequirementHash": 585769096,
    "runOnlyAcquisitionRewardSite": false
  },
  "stateInfo": {
    "requirements": {
      "entitlementUnavailableMessage": ""
    }
  },
  "presentationNodeType": 1,
  "traitIds": [],
  "traitHashes": [],
  "parentNodeHashes": [
    219546648
  ],
  "hash": 1350262226,
  "index": 8846,
  "redacted": false,
  "blacklisted": false
}
