{
  "displayProperties": {
    "description": "Équipez cet ornement sur n'importe quelle pièce d'armure légendaire pour changer son apparence. Une fois un ornement universel obtenu, il est disponible pour tous les personnages de la même classe d'un compte.",
    "name": "Veste chtonienne",
    "icon": "/common/destiny2_content/icons/4cab4eb072951b1bab2f499c485b5a25.jpg",
    "iconHash": 0,
    "hasIcon": true
  },
  "scope": 0,
  "sourceString": "Source : Everversum",
  "sourceHash": 860688654,
  "itemHash": 3560184043,
  "acquisitionInfo": {
    "runOnlyAcquisitionRewardSite": false
  },
  "stateInfo": {
    "requirements": {
      "entitlementUnavailableMessage": ""
    }
  },
  "presentationNodeType": 1,
  "traitIds": [],
  "traitHashes": [],
  "parentNodeHashes": [
    3353159818
  ],
  "hash": 1566138868,
  "index": 1025,
  "redacted": false,
  "blacklisted": false
}
