{
  "displayProperties": {
    "description": "Équipez-vous de ce revêtement pour modifier la couleur de votre équipement.",
    "name": "Liens célestes",
    "icon": "/common/destiny2_content/icons/634c48b43d2dc5330eda79e44eb0083d.jpg",
    "iconHash": 0,
    "hasIcon": true
  },
  "scope": 0,
  "sourceString": "Source : Débloqué par une offre spéciale.",
  "sourceHash": 1358645302,
  "itemHash": 4198291900,
  "acquisitionInfo": {
    "runOnlyAcquisitionRewardSite": false
  },
  "stateInfo": {
    "requirements": {
      "entitlementUnavailableMessage": ""
    }
  },
  "presentationNodeType": 1,
  "traitIds": [],
  "traitHashes": [],
  "parentNodeHashes": [
    2063273188
  ],
  "hash": 2953329980,
  "index": 7759,
  "redacted": false,
  "blacklisted": false
}
