{
  "displayProperties": {
    "description": "",
    "name": "Поножи отъявленного потрошителя",
    "icon": "/common/destiny2_content/icons/8fe50ee70872a4ccbf6ccc59e4738fcf.jpg",
    "iconHash": 0,
    "hasIcon": true
  },
  "scope": 1,
  "sourceString": "Источник: завершайте матчи Гамбита Прайм и повышайте свой ранг.",
  "sourceHash": 1952675042,
  "itemHash": 2094288641,
  "acquisitionInfo": {
    "runOnlyAcquisitionRewardSite": false
  },
  "stateInfo": {
    "requirements": {
      "entitlementUnavailableMessage": ""
    }
  },
  "presentationNodeType": 2,
  "traitIds": [],
  "traitHashes": [],
  "parentNodeHashes": [
    39044406,
    2516153921
  ],
  "hash": 2963735964,
  "index": 1739,
  "redacted": false,
  "blacklisted": false
}
