{
  "displayProperties": {
    "description": "Наденьте это украшение на любой элемент легендарной брони, чтобы изменить его внешний вид. Как только вы получаете универсальное украшение, оно открывается для всех персонажей соответствующего класса в вашей учетной записи.",
    "name": "Плащ «Яд»",
    "icon": "/common/destiny2_content/icons/47952f8f8dfcb8fe9902f56ba9a267ef.jpg",
    "iconHash": 0,
    "hasIcon": true
  },
  "scope": 0,
  "sourceString": "Источник: Эверверс",
  "sourceHash": 860688654,
  "itemHash": 3184812876,
  "acquisitionInfo": {
    "runOnlyAcquisitionRewardSite": false
  },
  "stateInfo": {
    "requirements": {
      "entitlementUnavailableMessage": ""
    }
  },
  "presentationNodeType": 1,
  "traitIds": [],
  "traitHashes": [],
  "parentNodeHashes": [
    250493616
  ],
  "hash": 3216755397,
  "index": 1223,
  "redacted": false,
  "blacklisted": false
}
