{
  "displayProperties": {
    "description": "",
    "name": "Оболочка «Геральдическая»",
    "icon": "/common/destiny2_content/icons/028f91d9857b7926f177c843cd7b36a8.jpg",
    "iconHash": 0,
    "hasIcon": true
  },
  "scope": 0,
  "sourceString": "Источник: яркие энграммы.",
  "sourceHash": 4036739795,
  "itemHash": 2833999149,
  "acquisitionInfo": {
    "acquireMaterialRequirementHash": 245139275,
    "runOnlyAcquisitionRewardSite": false
  },
  "stateInfo": {
    "requirements": {
      "entitlementUnavailableMessage": ""
    }
  },
  "presentationNodeType": 1,
  "traitIds": [],
  "traitHashes": [],
  "parentNodeHashes": [
    4165122677
  ],
  "hash": 3836105354,
  "index": 5123,
  "redacted": false,
  "blacklisted": false
}
