{
  "displayProperties": {
    "description": "",
    "name": "Kein Spielraum",
    "icon": "/common/destiny2_content/icons/52d3997927ab966432924c839fe61962.jpg",
    "iconHash": 0,
    "highResIcon": "/common/destiny2_content/icons/fc5fe30ebdc51588bc88e045b8d3614e.jpg",
    "hasIcon": true
  },
  "scope": 0,
  "sourceString": "Quelle: Everversum",
  "sourceHash": 860688654,
  "itemHash": 2862488832,
  "acquisitionInfo": {
    "acquireMaterialRequirementHash": 2463837317,
    "runOnlyAcquisitionRewardSite": false
  },
  "stateInfo": {
    "requirements": {
      "entitlementUnavailableMessage": ""
    }
  },
  "presentationNodeType": 1,
  "traitIds": [],
  "traitHashes": [],
  "parentNodeHashes": [
    3030939319
  ],
  "hash": 1175350614,
  "index": 9092,
  "redacted": false,
  "blacklisted": false
}
