{
  "displayProperties": {
    "description": "",
    "name": "Venns Pulsar",
    "icon": "/common/destiny2_content/icons/0ae9b0d94e4164f81e9be2b1def70872.jpg",
    "iconHash": 0,
    "hasIcon": true
  },
  "scope": 0,
  "sourceString": "Quelle: Durch ein spezielles Angebot freigeschaltet.",
  "sourceHash": 1358645302,
  "itemHash": 1885107807,
  "acquisitionInfo": {
    "runOnlyAcquisitionRewardSite": false
  },
  "stateInfo": {
    "requirements": {
      "entitlementUnavailableMessage": "Exklusiver Gegenstand"
    }
  },
  "presentationNodeType": 1,
  "traitIds": [],
  "traitHashes": [],
  "parentNodeHashes": [
    1166184619
  ],
  "hash": 1989835621,
  "index": 6323,
  "redacted": false,
  "blacklisted": false
}
