{
  "displayProperties": {
    "description": "",
    "name": "自尊之爪IV",
    "icon": "/common/destiny2_content/icons/e0aa0a877d410201e7fbf707bddecae8.jpg",
    "iconHash": 0,
    "hasIcon": true
  },
  "scope": 1,
  "sourceString": "來源：從愛蔻拉．蕾獲得升階禮包。",
  "sourceHash": 3075817319,
  "itemHash": 1390681142,
  "acquisitionInfo": {
    "acquireMaterialRequirementHash": 983547049,
    "runOnlyAcquisitionRewardSite": false
  },
  "stateInfo": {
    "requirements": {
      "entitlementUnavailableMessage": ""
    }
  },
  "presentationNodeType": 2,
  "traitIds": [],
  "traitHashes": [],
  "parentNodeHashes": [
    2389993857
  ],
  "hash": 1230036252,
  "index": 3657,
  "redacted": false,
  "blacklisted": false
}
