{
  "displayProperties": {
    "description": "一個訂製的加密工具，用來與戰爭智能進行機密通訊。",
    "name": "熾天使暗號",
    "icon": "/common/destiny2_content/icons/b55c0f276d1d8b303b20817141ccf166.jpg",
    "iconHash": 0,
    "hasIcon": true
  },
  "scope": 0,
  "sourceString": "來源：熾天季節",
  "sourceHash": 3574140916,
  "itemHash": 1884588413,
  "acquisitionInfo": {
    "runOnlyAcquisitionRewardSite": false
  },
  "stateInfo": {
    "requirements": {
      "entitlementUnavailableMessage": ""
    }
  },
  "presentationNodeType": 1,
  "traitIds": [],
  "traitHashes": [],
  "parentNodeHashes": [
    1484033736
  ],
  "hash": 3008645161,
  "index": 4422,
  "redacted": false,
  "blacklisted": false
}
