{
  "displayProperties": {
    "description": "",
    "name": "Overnight Dance",
    "icon": "/common/destiny2_content/icons/6a24c3dac5f03dd8eb59c797734f42ee.jpg",
    "iconHash": 0,
    "hasIcon": true
  },
  "scope": 0,
  "sourceString": "Source: Bright Engrams",
  "sourceHash": 4036739795,
  "itemHash": 799898425,
  "acquisitionInfo": {
    "runOnlyAcquisitionRewardSite": false
  },
  "stateInfo": {
    "requirements": {
      "entitlementUnavailableMessage": ""
    }
  },
  "presentationNodeType": 1,
  "traitIds": [],
  "traitHashes": [],
  "parentNodeHashes": [
    304361726
  ],
  "hash": 1666608006,
  "index": 6999,
  "redacted": false,
  "blacklisted": false
}
