{
  "displayProperties": {
    "description": "",
    "name": "Second Chance",
    "icon": "/common/destiny2_content/icons/6285bc3045fff252f74d0fcf614a4688.jpg",
    "iconHash": 0,
    "hasIcon": true
  },
  "scope": 1,
  "sourceString": "Exotic Armor Focusing",
  "sourceHash": 4011186136,
  "itemHash": 4268030601,
  "acquisitionInfo": {
    "acquireMaterialRequirementHash": 1920773870,
    "runOnlyAcquisitionRewardSite": false
  },
  "stateInfo": {
    "requirements": {
      "entitlementUnavailableMessage": ""
    }
  },
  "presentationNodeType": 2,
  "traitIds": [],
  "traitHashes": [],
  "parentNodeHashes": [
    1024582165,
    2598675734
  ],
  "hash": 2589037677,
  "index": 4498,
  "redacted": false,
  "blacklisted": false
}
