{
  "displayProperties": {
    "description": "",
    "name": "불법 침입자 로브",
    "icon": "/common/destiny2_content/icons/6f2aeab4084db1c2acde9ba8bc7ef220.jpg",
    "iconHash": 0,
    "hasIcon": true
  },
  "scope": 1,
  "sourceString": "출처: 쥴",
  "sourceHash": 3845969330,
  "itemHash": 727872428,
  "acquisitionInfo": {
    "runOnlyAcquisitionRewardSite": false
  },
  "stateInfo": {
    "requirements": {
      "entitlementUnavailableMessage": ""
    }
  },
  "presentationNodeType": 1,
  "traitIds": [],
  "traitHashes": [],
  "parentNodeHashes": [
    1976484181
  ],
  "hash": 1092783922,
  "index": 3203,
  "redacted": false,
  "blacklisted": false
}
