{
  "displayProperties": {
    "description": "",
    "name": "크루오리스 FR4",
    "icon": "/common/destiny2_content/icons/a5918085374a4c0ec8c7c44329982086.jpg",
    "iconHash": 0,
    "hasIcon": true
  },
  "scope": 0,
  "sourceString": "출처: 전설 엔그램을 열고 진영 등급 상승 패키지 획득.",
  "sourceHash": 3334812276,
  "itemHash": 891996636,
  "acquisitionInfo": {
    "runOnlyAcquisitionRewardSite": false
  },
  "stateInfo": {
    "requirements": {
      "entitlementUnavailableMessage": ""
    }
  },
  "presentationNodeType": 2,
  "traitIds": [],
  "traitHashes": [],
  "parentNodeHashes": [
    2122496537
  ],
  "hash": 1817434380,
  "index": 9429,
  "redacted": false,
  "blacklisted": false
}
