{
  "displayProperties": {
    "description": "네소스에 숨겨진 상자에서만 찾을 수 있는 희귀 문양입니다.",
    "name": "리바이어던의 축제",
    "icon": "/common/destiny2_content/icons/9e8c63512f4d1233870c7083c3871fb8.jpg",
    "iconHash": 0,
    "hasIcon": true
  },
  "scope": 0,
  "sourceString": "",
  "sourceHash": 3389857033,
  "itemHash": 776878385,
  "acquisitionInfo": {
    "runOnlyAcquisitionRewardSite": false
  },
  "stateInfo": {
    "requirements": {
      "entitlementUnavailableMessage": ""
    }
  },
  "presentationNodeType": 1,
  "traitIds": [],
  "traitHashes": [],
  "parentNodeHashes": [
    631010939
  ],
  "hash": 2648203367,
  "index": 6910,
  "redacted": false,
  "blacklisted": false
}
