{
  "displayProperties": {
    "description": "벌레의 속삭임에 장착하여 외양을 바꾸는 무기 장식입니다. 획득한 장식은 계정 내 모든 캐릭터에 사용할 수 있습니다.",
    "name": "숨결 사이",
    "icon": "/common/destiny2_content/icons/fa5820a5de9d9d5582ce135632978284.jpg",
    "iconHash": 0,
    "highResIcon": "/common/destiny2_content/icons/0a11ddce2ca8ce596275995710b3851c.jpg",
    "hasIcon": true
  },
  "scope": 0,
  "sourceString": "출처: 에버버스",
  "sourceHash": 860688654,
  "itemHash": 1906359096,
  "acquisitionInfo": {
    "runOnlyAcquisitionRewardSite": false
  },
  "stateInfo": {
    "requirements": {
      "entitlementUnavailableMessage": ""
    }
  },
  "presentationNodeType": 1,
  "traitIds": [],
  "traitHashes": [],
  "parentNodeHashes": [
    1155210481
  ],
  "hash": 38614810,
  "index": 5038,
  "redacted": false,
  "blacklisted": false
}
