{
  "displayProperties": {
    "description": "",
    "name": "머나먼 해일",
    "icon": "/common/destiny2_content/icons/65f2de7e265f9ee9a2b0f5eea443f7e2.jpg",
    "iconHash": 0,
    "hasIcon": true
  },
  "scope": 0,
  "sourceString": "출처: 특별 보상으로 잠금 해제됨.",
  "sourceHash": 1358645302,
  "itemHash": 2962058737,
  "acquisitionInfo": {
    "runOnlyAcquisitionRewardSite": false
  },
  "stateInfo": {
    "requirements": {
      "entitlementUnavailableMessage": "고유 아이템"
    }
  },
  "presentationNodeType": 1,
  "traitIds": [],
  "traitHashes": [],
  "parentNodeHashes": [
    1166184619
  ],
  "hash": 4137754763,
  "index": 6241,
  "redacted": false,
  "blacklisted": false
}
