{
  "displayProperties": {
    "description": "천둥의 왕에 장착하여 외양을 바꾸는 무기 장식입니다. 획득한 장식은 계정 내 모든 캐릭터에서 사용할 수 있습니다.",
    "name": "틀랄록의 분노",
    "icon": "/common/destiny2_content/icons/c9cedf331ce74a2dad14c8069ff23778.jpg",
    "iconHash": 0,
    "highResIcon": "/common/destiny2_content/icons/834dc177526dd4d6a118e77a43988b13.jpg",
    "hasIcon": true
  },
  "scope": 0,
  "sourceString": "출처: 에버버스",
  "sourceHash": 860688654,
  "itemHash": 1021939294,
  "acquisitionInfo": {
    "runOnlyAcquisitionRewardSite": false
  },
  "stateInfo": {
    "requirements": {
      "entitlementUnavailableMessage": ""
    }
  },
  "presentationNodeType": 1,
  "traitIds": [],
  "traitHashes": [],
  "parentNodeHashes": [
    196137750
  ],
  "hash": 562080172,
  "index": 4906,
  "redacted": false,
  "blacklisted": false
}
