{
  "displayProperties": {
    "description": "",
    "name": "총제작자의 헌신 왕관",
    "icon": "/common/destiny2_content/icons/fb76395c73a5be3cbe2ce029b668aacc.jpg",
    "iconHash": 0,
    "hasIcon": true
  },
  "scope": 1,
  "sourceString": "출처: \"과거의 고통\" 레이드에서 획득.",
  "sourceHash": 4246883461,
  "itemHash": 583145321,
  "acquisitionInfo": {
    "runOnlyAcquisitionRewardSite": false
  },
  "stateInfo": {
    "requirements": {
      "entitlementUnavailableMessage": ""
    }
  },
  "presentationNodeType": 2,
  "traitIds": [],
  "traitHashes": [],
  "parentNodeHashes": [
    1114960391
  ],
  "hash": 693621253,
  "index": 3266,
  "redacted": false,
  "blacklisted": false
}
