{
  "displayProperties": {
    "description": "실천의 칼날에 장착하여 외양을 바꾸는 무기 장식입니다. 획득한 장식은 계정 내 모든 캐릭터에 사용할 수 있습니다.",
    "name": "황금기 검자루",
    "icon": "/common/destiny2_content/icons/03ea12573f5c1b298f1451144382ee42.jpg",
    "iconHash": 0,
    "highResIcon": "/common/destiny2_content/icons/f70e3e31758f791b4c34d1d2c353ea88.jpg",
    "hasIcon": true
  },
  "scope": 0,
  "sourceString": "출처: 에버버스",
  "sourceHash": 860688654,
  "itemHash": 107372146,
  "acquisitionInfo": {
    "runOnlyAcquisitionRewardSite": false
  },
  "stateInfo": {
    "requirements": {
      "entitlementUnavailableMessage": ""
    }
  },
  "presentationNodeType": 1,
  "traitIds": [],
  "traitHashes": [],
  "parentNodeHashes": [
    895842570
  ],
  "hash": 829206924,
  "index": 5085,
  "redacted": false,
  "blacklisted": false
}
