{
  "displayProperties": {
    "description": "이 안료를 적용하면 장비의 색상을 바꿀 수 있습니다.",
    "name": "코발트 격돌",
    "icon": "/common/destiny2_content/icons/b382e51ee7c115322fbfa18b228344d7.jpg",
    "iconHash": 0,
    "hasIcon": true
  },
  "scope": 0,
  "sourceString": "출처: 무결점 시험 티켓 완료.",
  "sourceHash": 3543690049,
  "itemHash": 3110332187,
  "acquisitionInfo": {
    "runOnlyAcquisitionRewardSite": false
  },
  "stateInfo": {
    "requirements": {
      "entitlementUnavailableMessage": ""
    }
  },
  "presentationNodeType": 1,
  "traitIds": [],
  "traitHashes": [],
  "parentNodeHashes": [
    1657213183
  ],
  "hash": 904665892,
  "index": 7662,
  "redacted": false,
  "blacklisted": false
}
