{
  "displayProperties": {
    "description": "",
    "name": "Único sobreviviente",
    "icon": "/common/destiny2_content/icons/15b6dc0103016791925d0ca2284aeed6.jpg",
    "iconHash": 0,
    "hasIcon": true
  },
  "scope": 0,
  "sourceString": "Fuente: Pesca en la Temporada de las Profundidades",
  "sourceHash": 2257836668,
  "itemHash": 1150492185,
  "acquisitionInfo": {
    "runOnlyAcquisitionRewardSite": false
  },
  "stateInfo": {
    "requirements": {
      "entitlementUnavailableMessage": ""
    }
  },
  "presentationNodeType": 2,
  "traitIds": [],
  "traitHashes": [],
  "parentNodeHashes": [
    1186584658
  ],
  "hash": 2167525566,
  "index": 9630,
  "redacted": false,
  "blacklisted": false
}
