{
  "displayProperties": {
    "description": "",
    "name": "Probabilidad sutil",
    "icon": "/common/destiny2_content/icons/cb8f96637e2d8d52b034e48f67e2398c.jpg",
    "iconHash": 0,
    "hasIcon": true
  },
  "scope": 0,
  "sourceString": "Fuente: Engramas brillantes",
  "sourceHash": 4036739795,
  "itemHash": 1264663103,
  "acquisitionInfo": {
    "acquireMaterialRequirementHash": 585769096,
    "runOnlyAcquisitionRewardSite": false
  },
  "stateInfo": {
    "requirements": {
      "entitlementUnavailableMessage": ""
    }
  },
  "presentationNodeType": 1,
  "traitIds": [],
  "traitHashes": [],
  "parentNodeHashes": [
    4123540759
  ],
  "hash": 2527722412,
  "index": 8983,
  "redacted": false,
  "blacklisted": false
}
