{
  "displayProperties": {
    "description": "Equipa este shader para cambiar el color de tu equipamiento.",
    "name": "Efigie de mármol",
    "icon": "/common/destiny2_content/icons/c5989490b99b33df06705104a8ccf0b4.jpg",
    "iconHash": 0,
    "hasIcon": true
  },
  "scope": 0,
  "sourceString": "Fuente: Completa partidas del Estandarte de Hierro y gana paquetes de subida de rango con Lord Saladino.",
  "sourceHash": 3072862693,
  "itemHash": 2532730764,
  "acquisitionInfo": {
    "runOnlyAcquisitionRewardSite": false
  },
  "stateInfo": {
    "requirements": {
      "entitlementUnavailableMessage": ""
    }
  },
  "presentationNodeType": 1,
  "traitIds": [],
  "traitHashes": [],
  "parentNodeHashes": [
    1657213183
  ],
  "hash": 2666223615,
  "index": 7604,
  "redacted": false,
  "blacklisted": false
}
