{
  "displayProperties": {
    "description": "この破片は暗黒エネルギーと共鳴し、触ると暖かい。ペトラ・ベンジと夢見る都市のテクナ・ウィッチが使いみちを知っているかもしれない。",
    "name": "暗黒の破片",
    "icon": "/common/destiny2_content/icons/f7d9cc435fb93b494e8a9ca9593d4794.jpg",
    "iconHash": 0,
    "hasIcon": true
  },
  "scope": 0,
  "sourceString": "入手方法: 夢見る都市でアクティビティを完了",
  "sourceHash": 2559145507,
  "itemHash": 1633854071,
  "acquisitionInfo": {
    "runOnlyAcquisitionRewardSite": false
  },
  "stateInfo": {
    "requirements": {
      "entitlementUnavailableMessage": ""
    }
  },
  "presentationNodeType": 1,
  "traitIds": [],
  "traitHashes": [],
  "parentNodeHashes": [
    1828392375
  ],
  "hash": 2348878993,
  "index": 10973,
  "redacted": false,
  "blacklisted": false
}
