{
  "displayProperties": {
    "description": "",
    "name": "アイオン順応のバンド",
    "icon": "/common/destiny2_content/icons/ed84553c654e3c5a74c83efa5354ffd8.jpg",
    "iconHash": 0,
    "hasIcon": true
  },
  "scope": 1,
  "sourceString": "入手方法: ケプラーの探索",
  "sourceHash": 4284811963,
  "itemHash": 119770768,
  "acquisitionInfo": {
    "acquireMaterialRequirementHash": 983547049,
    "runOnlyAcquisitionRewardSite": false
  },
  "stateInfo": {
    "requirements": {
      "entitlementUnavailableMessage": ""
    }
  },
  "presentationNodeType": 2,
  "traitIds": [],
  "traitHashes": [],
  "parentNodeHashes": [
    1469373075
  ],
  "hash": 2882728037,
  "index": 3849,
  "redacted": false,
  "blacklisted": false
}
