{
  "displayProperties": {
    "description": "",
    "name": "冬至",
    "icon": "/common/destiny2_content/icons/a8ce793afc9166a30c363acf443f9817.jpg",
    "iconHash": 0,
    "hasIcon": true
  },
  "scope": 0,
  "sourceString": "入手方法: シーズンイベント暁旦",
  "sourceHash": 4054646289,
  "itemHash": 2680217527,
  "acquisitionInfo": {
    "runOnlyAcquisitionRewardSite": false
  },
  "stateInfo": {
    "requirements": {
      "entitlementUnavailableMessage": ""
    }
  },
  "presentationNodeType": 1,
  "traitIds": [],
  "traitHashes": [],
  "parentNodeHashes": [
    2451657441
  ],
  "hash": 3140613135,
  "index": 6820,
  "redacted": false,
  "blacklisted": false
}
