{
  "displayProperties": {
    "description": "",
    "name": "バイスロイのシェル",
    "icon": "/common/destiny2_content/icons/19edfea45eb766766dc49ecbeceb8eed.jpg",
    "iconHash": 0,
    "hasIcon": true
  },
  "scope": 0,
  "sourceString": "入手方法: ブライトエングラム",
  "sourceHash": 4036739795,
  "itemHash": 89965906,
  "acquisitionInfo": {
    "acquireMaterialRequirementHash": 245139275,
    "runOnlyAcquisitionRewardSite": false
  },
  "stateInfo": {
    "requirements": {
      "entitlementUnavailableMessage": ""
    }
  },
  "presentationNodeType": 1,
  "traitIds": [],
  "traitHashes": [],
  "parentNodeHashes": [
    1440198332
  ],
  "hash": 525581019,
  "index": 5155,
  "redacted": false,
  "blacklisted": false
}
