{
  "displayProperties": {
    "description": "Applica questo decoro su un pezzo di armatura leggendaria idoneo per cambiarne l'aspetto. Una volta ottenuto un decoro universale, questo si sblocca per tutti i personaggi della rispettiva classe sull'account.",
    "name": "Marchio della Potenza del leone",
    "icon": "/common/destiny2_content/icons/54ff337c8b23dc094f323b8e35b8adc1.jpg",
    "iconHash": 0,
    "highResIcon": "/common/destiny2_content/icons/15deb463b4872181b85f6af90718867d.jpg",
    "hasIcon": true
  },
  "scope": 0,
  "sourceString": "Fonte: Everversum.",
  "sourceHash": 860688654,
  "itemHash": 146910655,
  "acquisitionInfo": {
    "runOnlyAcquisitionRewardSite": false
  },
  "stateInfo": {
    "requirements": {
      "entitlementUnavailableMessage": ""
    }
  },
  "presentationNodeType": 1,
  "traitIds": [],
  "traitHashes": [],
  "parentNodeHashes": [
    4066557610
  ],
  "hash": 1127888190,
  "index": 2872,
  "redacted": false,
  "blacklisted": false
}
