{
  "displayProperties": {
    "description": "Applica questo decoro per cambiare l'aspetto di Jötunn. Una volta ottenuto un decoro, esso si sblocca su tutti i personaggi dell'account.",
    "name": "Tracciasogni",
    "icon": "/common/destiny2_content/icons/8743f9d73e50a74c1cbb474f30b5063a.jpg",
    "iconHash": 0,
    "highResIcon": "/common/destiny2_content/icons/f702e9089f0fa8ba2c04c0d4effe2293.jpg",
    "hasIcon": true
  },
  "scope": 0,
  "sourceString": "Fonte: Everversum.",
  "sourceHash": 860688654,
  "itemHash": 2272772784,
  "acquisitionInfo": {
    "runOnlyAcquisitionRewardSite": false
  },
  "stateInfo": {
    "requirements": {
      "entitlementUnavailableMessage": ""
    }
  },
  "presentationNodeType": 1,
  "traitIds": [],
  "traitHashes": [],
  "parentNodeHashes": [
    2737711334
  ],
  "hash": 3477417490,
  "index": 4786,
  "redacted": false,
  "blacklisted": false
}
