{
  "displayProperties": {
    "description": "仅可在赫拉斯盆地的隐藏宝箱中找到这个稀少的徽标。",
    "name": "战争思维的堡垒",
    "icon": "/common/destiny2_content/icons/c8b0b2e2379605ddd5254dcd17432a36.jpg",
    "iconHash": 0,
    "hasIcon": true
  },
  "scope": 0,
  "sourceString": "",
  "sourceHash": 3389857033,
  "itemHash": 842157717,
  "acquisitionInfo": {
    "runOnlyAcquisitionRewardSite": false
  },
  "stateInfo": {
    "requirements": {
      "entitlementUnavailableMessage": ""
    }
  },
  "presentationNodeType": 1,
  "traitIds": [],
  "traitHashes": [],
  "parentNodeHashes": [
    631010939
  ],
  "hash": 4259147767,
  "index": 6923,
  "redacted": false,
  "blacklisted": false
}
