{
  "displayProperties": {
    "description": "在任意合适的传奇护甲物品上装备此皮肤以改变它的外观。你账号中的所有相关角色都将解锁获得的通用皮肤。",
    "name": "冰冻圈法袍",
    "icon": "/common/destiny2_content/icons/a02a342c5d7fb33a30907ce2b84162ec.jpg",
    "iconHash": 0,
    "highResIcon": "/common/destiny2_content/icons/921a1977d32647893abe8b04c9cfd816.jpg",
    "hasIcon": true
  },
  "scope": 1,
  "sourceString": "来源：永恒之诗",
  "sourceHash": 860688654,
  "itemHash": 802574732,
  "acquisitionInfo": {
    "runOnlyAcquisitionRewardSite": false
  },
  "stateInfo": {
    "requirements": {
      "entitlementUnavailableMessage": ""
    }
  },
  "presentationNodeType": 1,
  "traitIds": [],
  "traitHashes": [],
  "parentNodeHashes": [
    2503471334
  ],
  "hash": 585271049,
  "index": 4261,
  "redacted": false,
  "blacklisted": false
}
