{
  "displayProperties": {
    "description": "在任意合适的传奇护甲物品上装备此皮肤以改变它的外观。你账号中的所有相关角色都将解锁获得的通用皮肤。",
    "name": "竞技精神手套",
    "icon": "/common/destiny2_content/icons/f9906a9910c8ac1e4cd515c753910d0e.jpg",
    "iconHash": 0,
    "hasIcon": true
  },
  "scope": 0,
  "sourceString": "来源：永恒之诗",
  "sourceHash": 860688654,
  "itemHash": 3120368538,
  "acquisitionInfo": {
    "runOnlyAcquisitionRewardSite": false
  },
  "stateInfo": {
    "requirements": {
      "entitlementUnavailableMessage": ""
    }
  },
  "presentationNodeType": 1,
  "traitIds": [],
  "traitHashes": [],
  "parentNodeHashes": [
    1940059993
  ],
  "hash": 591927338,
  "index": 4369,
  "redacted": false,
  "blacklisted": false
}
